coolparse/__init__.py
coolparse-0.1.0.dist-info/LICENSE.txt
coolparse-0.1.0.dist-info/METADATA
coolparse-0.1.0.dist-info/WHEEL
coolparse-0.1.0.dist-info/top_level.txt
coolparse-0.1.0.dist-info/RECORD
