Metadata-Version: 2.1
Name: coolparse
Version: 0.1.0
Summary: coolparse
Author-email: Johannes <johannes-computer@mailfence.com>
License: The MIT License (MIT)
Project-URL: Download, https://pypi.org/project/coolparse/#files
Project-URL: Source, https://github.com/johannes-computer/coolparse
Classifier: License :: OSI Approved :: MIT License
Classifier: Programming Language :: Python
Classifier: Programming Language :: Python :: 3
Requires-Python: >=3.11
License-File: LICENSE.txt
